mbq/__init__.py
mbq/tokens/__init__.py
mbq/tokens/decoder.py
mbq/tokens/exceptions.py
mbq.tokens-0.0.1.dist-info/DESCRIPTION.rst
mbq.tokens-0.0.1.dist-info/METADATA
mbq.tokens-0.0.1.dist-info/RECORD
mbq.tokens-0.0.1.dist-info/WHEEL
mbq.tokens-0.0.1.dist-info/metadata.json
mbq.tokens-0.0.1.dist-info/top_level.txt
mbq.tokens-0.0.1.dist-info/zip-safe
tests/__init__.py
tests/compat.py
tests/test_decoder.py
tests/test_init.py
