Metadata-Version: 2.0
Name: mbq.tokens
Version: 0.0.1
Summary: UNKNOWN
Home-page: https://github.com/managedbyq/mbq.tokens
Author: Managed by Q, Inc.
Author-email: open-source@managedbyq.com
License: Apache 2.0
Keywords: jwt token authorization
Platform: UNKNOWN
Classifier: Development Status :: 5 - Production/Stable
Classifier: Intended Audience :: Developers
Classifier: License :: OSI Approved :: Apache Software License
Classifier: Operating System :: OS Independent
Classifier: Programming Language :: Python :: 2
Classifier: Programming Language :: Python :: 2.7
Classifier: Programming Language :: Python :: 3
Classifier: Programming Language :: Python :: 3.5
Classifier: Programming Language :: Python :: 3.6
Classifier: Topic :: Software Development :: Libraries
Requires-Dist: cryptography (==1.8.1)
Requires-Dist: pyjwt (==1.5.0)
